bien-1.0.2.dist-info/METADATA
bien-1.0.2.dist-info/WHEEL
bien-1.0.2.dist-info/licenses/LICENSE.txt
bien.py
noxfile.py
test_bien.py
bien-1.0.2.dist-info/RECORD
