Metadata-Version: 2.1
Name: bien
Version: 1.0.2
Summary: Component based HTML rendering for HTTP servers.
Author-Email: Zhaksylyk Beisenbayev <zhaks@use.startmail.com>
License: MIT
Requires-Python: <3.12,>=3.8
Provides-Extra: lint
Provides-Extra: test
Provides-Extra: ci
Requires-Dist: mypy<2,>=1.4.1; extra == "lint"
Requires-Dist: ruff<1,>=0.0.275; extra == "lint"
Requires-Dist: pytest<8,>=7.4.0; extra == "test"
Requires-Dist: pytest-cov<5,>=4.1.0; extra == "test"
Requires-Dist: nox>=2023.4.22; extra == "ci"
